philter_ucsf/__init__.py
philter_ucsf/__main__.py
philter_ucsf/coordinate_map.py
philter_ucsf/eval_scrubber_i2b2.py
philter_ucsf/eval_scrubber_ucsf.py
philter_ucsf/improve_i2b2_notes.py
philter_ucsf/philter.py
philter_ucsf/configs/philter_delta.json
philter_ucsf/data/phi_notes_i2b2.json
philter_ucsf/data/i2b2_anno/110-01.txt
philter_ucsf/data/i2b2_anno/110-02.txt
philter_ucsf/data/i2b2_anno/110-03.txt
philter_ucsf/data/i2b2_anno/110-04.txt
philter_ucsf/data/i2b2_anno/111-01.txt
philter_ucsf/data/i2b2_notes/110-01.txt
philter_ucsf/data/i2b2_notes/110-02.txt
philter_ucsf/data/i2b2_notes/110-03.txt
philter_ucsf/data/i2b2_notes/110-04.txt
philter_ucsf/data/i2b2_notes/111-01.txt
philter_ucsf/data/i2b2_xml/110-01.xml
philter_ucsf/data/i2b2_xml/110-02.xml
philter_ucsf/data/i2b2_xml/110-03.xml
philter_ucsf/data/i2b2_xml/110-04.xml
philter_ucsf/data/i2b2_xml/111-01.xml
philter_ucsf/data/phi/fn.txt
philter_ucsf/data/phi/fn_tags.txt
philter_ucsf/data/phi/fn_tags_context.txt
philter_ucsf/data/phi/fp.txt
philter_ucsf/data/phi/fp_tags.txt
philter_ucsf/data/phi/fp_tags_context.txt
philter_ucsf/data/phi/summary.json
philter_ucsf/filters/blacklists/firstnames_minus_fps.json
philter_ucsf/filters/blacklists/lastnames_minus_fps.json
philter_ucsf/filters/regex/transform_regex.py
philter_ucsf/filters/regex/addresses/at_address_noindicator.txt
philter_ucsf/filters/regex/addresses/at_address_noindicator_transformed.txt
philter_ucsf/filters/regex/addresses/at_street_dash_street.txt
philter_ucsf/filters/regex/addresses/at_street_dash_street_transformed.txt
philter_ucsf/filters/regex/addresses/at_street_number_dash_street.txt
philter_ucsf/filters/regex/addresses/at_street_number_dash_street_transformed.txt
philter_ucsf/filters/regex/addresses/box.txt
philter_ucsf/filters/regex/addresses/box_room.txt
philter_ucsf/filters/regex/addresses/box_room_transformed.txt
philter_ucsf/filters/regex/addresses/box_transformed.txt
philter_ucsf/filters/regex/addresses/city.txt
philter_ucsf-1.0.3.dist-info/LICENSE
philter_ucsf-1.0.3.dist-info/METADATA
philter_ucsf-1.0.3.dist-info/WHEEL
philter_ucsf-1.0.3.dist-info/top_level.txt
philter_ucsf-1.0.3.dist-info/RECORD
