Metadata-Version: 2.1
Name: philter-ucsf
Version: 1.0.3
Summary: An open-source PHI-filtering software
Home-page: https://github.com/BCHSI/philter-ucsf
Author: Beau Norgeot
Author-email: beaunorgeot@gmail.com
License: UNKNOWN
Platform: UNKNOWN
Classifier: Programming Language :: Python :: 3
Classifier: License :: OSI Approved :: BSD License
Classifier: Operating System :: OS Independent
